Semester 3/DSD/DSD Lab/Experiment 5/Question 3/Mooretype.v
module Mooretype(clk,rst,inp,out);
  input clk,rst,inp;
  output reg out;
  parameter A = 3'b000;
  parameter B = 3'b001;
  parameter C = 3'b010;
  parameter D = 3'b011;
  parameter E = 3'b100;
  parameter F = 3'b101;
  reg [2:0] state, nxt_state;
  always@(posedge clk , posedge rst) begin
    if(rst == 1)
      state <= A;
    else
      state <= nxt_state;
  end
  always@(state , inp) begin
    case(state)
      A : begin 
        if(inp == 1'b0)
          nxt_state <= A;
        else
          nxt_state <= B;
      end
      B : begin
        if(inp == 1'b0)
          nxt_state <= C;
        else
          nxt_state <= B;
      end
      C : begin
        if(inp == 1'b0)
          nxt_state <= A;
        else
          nxt_state <= D;
      end
      D : begin
        if(inp == 1'b0)
          nxt_state <= E;
        else 
          nxt_state <= B;
      end
      E : begin
        if(inp == 1'b0)
          nxt_state <= A;
        else
          nxt_state <= F;
      end
      F : begin
        if(inp == 1'b0)
          nxt_state <= A;
        else
          nxt_state <= B;
      end
      default : nxt_state <= A;
    endcase
  end
  always@(state) begin
    case(state)
      F : out <= 1;
      default : out <= 0;
    endcase
  end
endmodule

Semester 3/DSD/DSD Lab/Experiment 5/Question 3/testbenchE5Q3.v
module testbenchE5Q3();
  reg clk,rst,inp;
  wire out;
  Mooretype uut(clk,rst,inp,out);
  initial begin
    clk = 0;
    forever #5 clk = ~clk;
  end
  initial begin
    $monitor($time,": Input = %b , Output = %b",inp,out);
    inp = 0;
    rst = 1;
    #30 rst = 0;
    #40 inp = 0;
    #10 inp = 1;
    #10 inp = 0;
    #10 inp = 1;
    #10 inp = 1;
    #10 inp = 1;
    #10 inp = 0;
    #10 inp = 1;
    #10 inp = 0;
    #10 inp = 1;
    #10 inp = 0;
    #10 inp = 1;
    #100 $finish;
  end
 initial begin
   $dumpfile("dump.vcd"); 
   $dumpvars; 
 end
endmodule

Semester 3/DSD/DSD Lab/Experiment 5/Question 3/dump.vcd
$date
	Sat Nov 18 22:04:04 2023
$end
$version
	ModelSim Version 2020.1
$end
$timescale
	1ps
$end

$scope module testbenchE5Q3 $end
$var reg 1 ! clk $end
$var reg 1 " rst $end
$var reg 1 # inp $end
$var wire 1 $ out $end

$scope module uut $end
$var parameter 3 % A $end
$var parameter 3 & B $end
$var parameter 3 ' C $end
$var parameter 3 ( D $end
$var parameter 3 ) E $end
$var parameter 3 * F $end
$var wire 1 + clk $end
$var wire 1 , rst $end
$var wire 1 - inp $end
$var reg 1 . out $end
$var reg 3 / state [2:0] $end
$var reg 3 0 nxt_state [2:0] $end
$upscope $end
$upscope $end
$enddefinitions $end
#0
$dumpvars
0!
1"
0#
0.
b0 /
b0 0
b0 %
b1 &
b10 '
b11 (
b100 )
b101 *
0$
0-
1,
0+
$end
#5
1!
1+
#10
0!
0+
#15
1!
1+
#20
0!
0+
#25
1!
1+
#30
0"
0!
0,
0+
#35
1!
1+
#40
0!
0+
#45
1!
1+
#50
0!
0+
#55
1!
1+
#60
0!
0+
#65
1!
1+
#70
0!
0+
#75
1!
1+
#80
1#
0!
1-
0+
b1 0
#85
1!
1+
b1 /
#90
0#
0!
0-
0+
b10 0
#95
1!
1+
b10 /
b0 0
#100
1#
0!
1-
0+
b11 0
#105
1!
1+
b11 /
b1 0
#110
0!
0+
#115
1!
1+
b1 /
#120
0!
0+
#125
1!
1+
#130
0#
0!
0-
0+
b10 0
#135
1!
1+
b10 /
b0 0
#140
1#
0!
1-
0+
b11 0
#145
1!
1+
b11 /
b1 0
#150
0#
0!
0-
0+
b100 0
#155
1!
1+
b100 /
b0 0
#160
1#
0!
1-
0+
b101 0
#165
1!
1+
b101 /
1.
1$
b1 0
#170
0#
0!
0-
0+
b0 0
#175
1!
1+
b0 /
0.
0$
#180
1#
0!
1-
0+
b1 0
#185
1!
1+
b1 /
