Semester 3/DSD/DSD Lab/Experiment 2/HalfAdderSL.v
module haSL(sum,carry,a,b);
output sum, carry;
input a, b;
xor (sum, a, b);
and (carry, a, b);
endmodule

Semester 3/DSD/DSD Lab/Experiment 2/FullAdderHalfAdder.v
module faha(s, ca, a, b, c);
output s, ca;
input a,b, c;
wire hs, c1, c2;
haSL ha1(hs, c1, a, b);
haSL ha2(s, c2, hs, c);
or (ca, c1, c2);
endmodule

Semester 3/DSD/DSD Lab/Experiment 2/FullAdderTestbench.v
module fatestbench();
reg A, B, C;
wire S,CA;
faha fa(S, CA, A, B, C);
initial begin
$dumpfile("dump.vcd");
$monitor($time, "ns", "\t A=%b, B=%b, C=%b, Sum=%b, Carry=%b", A, B, C, S, CA);
$dumpvars(1, A);
$dumpvars(1, B);
$dumpvars(1, C);
$dumpvars(1, S);
$dumpvars(1, CA);
{A, B, C}={1'b0, 1'b0, 1'b0};
#50 {A, B, C}={1'b0, 1'b0, 1'b1};
#50 {A, B, C}={1'b0, 1'b1, 1'b0};
#50 {A, B, C}={1'b0, 1'b1, 1'b1};
#50 {A, B, C}={1'b1, 1'b0, 1'b0};
#50 {A, B, C}={1'b1, 1'b0, 1'b1};
#50 {A, B, C}={1'b1, 1'b1, 1'b0};
#50 {A, B, C}={1'b1, 1'b1, 1'b1};
end
endmodule

Semester 3/DSD/DSD Lab/Experiment 2/dump.vcd
$date
	Mon Oct 09 08:04:37 2023
$end
$version
	ModelSim Version 2020.1
$end
$timescale
	1ps
$end

$scope module fatestbench $end
$var reg 1 ! A $end
$var reg 1 " B $end
$var reg 1 # C $end
$var wire 1 $ S $end
$var wire 1 % CA $end
$upscope $end
$enddefinitions $end
#0
$dumpvars
0!
0"
0#
0$
0%
$end
#50
1#
1$
#100
0#
1"
0$
1$
#150
1#
0$
1%
#200
0#
0"
1!
1$
0%
#250
1#
0$
1%
#300
0#
1"
1$
0$
#350
1#
1$
