Semester 3/DSD/DSD Lab/Experiment 5/Question 2/VendingMachine.v
module VendingMachine(clk,rst,inp,out);
  input clk,rst;
  input [3:0] inp;
  output reg out;
  parameter A = 2'b00;
  parameter B = 2'b01;
  parameter C = 2'b10;
  reg [1:0] state, nxt_state;
  always@(posedge clk , posedge rst) begin
    if(rst == 1)
      state <= A;
    else
      state <= nxt_state;
  end
  always@(state , inp) begin
    case(state)
      A : begin 
        if(inp == 0)
	begin
          nxt_state <= A;
	  out = 0;
	end
        else if (inp == 5)
	begin
          nxt_state <= B;
	  out = 0;
	end
	else if (inp == 10)
	begin
	  nxt_state <= C;
	  out = 0;
	end
      end
      B : begin 
        if(inp == 0)
	begin
          nxt_state <= A;
	  out = 0;
	end
        else if (inp == 5)
	begin
          nxt_state <= C;
	  out = 0;
	end
	else if (inp == 10)
	begin
	  nxt_state <= A;
	  out = 1;
	end
      end
       C : begin 
        if(inp == 0)
	begin
          nxt_state <= A;
	  out = 0;
	end
        else if (inp == 5)
	begin
          nxt_state <= A;
	  out = 1;
	end
	else if (inp == 10)
	begin
	  nxt_state <= A;
	  out = 0;
	end
      end
      default : 
	begin
	  nxt_state <= A;
	  out = 0;
	end
    endcase
  end
endmodule

Semester 3/DSD/DSD Lab/Experiment 5/Question 2/testbenchE5Q2.v
module testbenchE5Q2;
  reg clk,rst; reg [3:0] inp;
  wire out;
  VendingMachine test(clk,rst,inp,out);
  initial begin
    clk = 0;
    forever #5 clk = ~clk;
  end
  initial begin
    $monitor($time,": Input = %d , Output = %b",inp,out);
    inp = 0;
    rst = 1;
    #30 rst = 0;
    #40 inp = 0;
    #10 inp = 5;
    #10 inp = 10;
    #10 inp = 10;
    #10 inp = 0;
    #10 inp = 10;
    #10 inp = 10;
    #10 inp = 5;
    #10 inp = 10;
    #10 inp = 10;
    #10 inp = 0;
    #10 inp = 5;
    #10 inp = 5;
    #10 inp = 10;
    #10 inp = 10;
    #10 inp = 0;
    #10 inp = 10;
    #10 inp = 10;
    #10 inp = 5;
    #10 inp = 10;
    #10 inp = 10;
    #10 inp = 0;
    #10 inp = 5;
    $stop;
  end
 initial begin
   $dumpfile("dump.vcd"); 
   $dumpvars; 
 end
endmodule

Semester 3/DSD/DSD Lab/Experiment 5/Question 2/dump.vcd
$date
	Fri Nov 10 21:47:00 2023
$end
$version
	ModelSim Version 2020.1
$end
$timescale
	1ps
$end

$scope module testbenchE5Q2 $end
$var reg 1 ! clk $end
$var reg 1 " rst $end
$var reg 4 # inp [3:0] $end
$var wire 1 $ out $end

$scope module test $end
$var parameter 2 % A $end
$var parameter 2 & B $end
$var parameter 2 ' C $end
$var wire 1 ( clk $end
$var wire 1 ) rst $end
$var wire 1 * inp [3] $end
$var wire 1 + inp [2] $end
$var wire 1 , inp [1] $end
$var wire 1 - inp [0] $end
$var reg 1 . out $end
$var reg 2 / state [1:0] $end
$var reg 2 0 nxt_state [1:0] $end
$upscope $end
$upscope $end
$enddefinitions $end
#0
$dumpvars
0!
1"
b0 #
0.
b0 /
b0 0
b0 %
b1 &
b10 '
0$
0-
0,
0+
0*
1)
0(
$end
#5
1!
1(
#10
0!
0(
#15
1!
1(
#20
0!
0(
#25
1!
1(
#30
0"
0!
0)
0(
#35
1!
1(
#40
0!
0(
#45
1!
1(
#50
0!
0(
#55
1!
1(
#60
0!
0(
#65
1!
1(
#70
0!
0(
#75
1!
1(
#80
b101 #
0!
1-
1+
0(
b1 0
#85
1!
1(
b1 /
b10 0
#90
b1010 #
0!
0-
1,
0+
1*
0(
1.
1$
b0 0
#95
1!
1(
b0 /
0.
0$
b10 0
#100
0!
0(
#105
1!
1(
b10 /
b0 0
#110
b0 #
0!
0,
0*
0(
#115
1!
1(
b0 /
#120
b1010 #
0!
1,
1*
0(
b10 0
#125
1!
1(
b10 /
b0 0
#130
0!
0(
#135
1!
1(
b0 /
b10 0
#140
b101 #
0!
1-
0,
1+
0*
0(
b1 0
#145
1!
1(
b1 /
b10 0
#150
b1010 #
0!
0-
1,
0+
1*
0(
1.
1$
b0 0
#155
1!
1(
b0 /
0.
0$
b10 0
#160
0!
0(
#165
1!
1(
b10 /
b0 0
#170
b0 #
0!
0,
0*
0(
#175
1!
1(
b0 /
#180
b101 #
0!
1-
1+
0(
b1 0
#185
1!
1(
b1 /
b10 0
#190
0!
0(
#195
1!
1(
b10 /
1.
1$
b0 0
#200
b1010 #
0!
0-
1,
0+
1*
0(
0.
0$
#205
1!
1(
b0 /
b10 0
#210
0!
0(
#215
1!
1(
b10 /
b0 0
#220
b0 #
0!
0,
0*
0(
#225
1!
1(
b0 /
#230
b1010 #
0!
1,
1*
0(
b10 0
#235
1!
1(
b10 /
b0 0
#240
0!
0(
#245
1!
1(
b0 /
b10 0
#250
b101 #
0!
1-
0,
1+
0*
0(
b1 0
#255
1!
1(
b1 /
b10 0
#260
b1010 #
0!
0-
1,
0+
1*
0(
1.
1$
b0 0
#265
1!
1(
b0 /
0.
0$
b10 0
#270
0!
0(
#275
1!
1(
b10 /
b0 0
#280
b0 #
0!
0,
0*
0(
#285
1!
1(
b0 /
#290
b101 #
